pyatmoweb/__init__.py
pyatmoweb/pyAtmoWeb.py
pyatmoweb-0.0.3.dist-info/licenses/LICENCE
pyatmoweb-0.0.3.dist-info/METADATA
pyatmoweb-0.0.3.dist-info/WHEEL
pyatmoweb-0.0.3.dist-info/top_level.txt
pyatmoweb-0.0.3.dist-info/RECORD
