Metadata-Version: 2.4
Name: pyatmoweb
Version: 0.0.3
Summary: PyAtmoWeb helpers
Author-email: Enno Henn <henn@ipfdd.de>
Requires-Python: >=3.8
License-File: LICENCE
Requires-Dist: requests
Dynamic: license-file
